matchmaker/wsgi.py
matchmaker/application/NextRoundMatchesTypes.py
matchmaker/application/QueryContext.py
matchmaker/application/__init__.py
matchmaker/application/matchmaker.py
matchmaker/application/routes.py
matchmaker_t4_arm-0.1.6.dist-info/LICENSE
matchmaker_t4_arm-0.1.6.dist-info/METADATA
matchmaker_t4_arm-0.1.6.dist-info/WHEEL
matchmaker_t4_arm-0.1.6.dist-info/top_level.txt
matchmaker_t4_arm-0.1.6.dist-info/RECORD
